rerank_feature_generator/.DS_Store
rerank_feature_generator/__init__.py
rerank_feature_generator/generate_feature.py
rerank_feature_generator/generate_idf.py
rerank_feature_generator/idf.txt
rerank_feature_generator/utils.py
rerank_feature_generator-1.0.11.dist-info/METADATA
rerank_feature_generator-1.0.11.dist-info/WHEEL
rerank_feature_generator-1.0.11.dist-info/top_level.txt
rerank_feature_generator-1.0.11.dist-info/RECORD
